swap_exceptions/__init__.py
swap_exceptions-1.0.2.dist-info/LICENSE
swap_exceptions-1.0.2.dist-info/WHEEL
swap_exceptions-1.0.2.dist-info/METADATA
swap_exceptions-1.0.2.dist-info/RECORD
