Metadata-Version: 2.1
Name: swap-exceptions
Version: 1.0.2
Summary: Python utility decorator and context manager for swapping exceptions
Home-page: https://github.com/tomgrin10/swap-exceptions
License: MIT
Keywords: swap,exceptions,switch,replace,utility
Author: Tom Gringauz
Author-email: tomgrin10@gmail.com
Requires-Python: >=2.7, !=3.0.*, !=3.1.*, !=3.2.*, !=3.3.*, !=3.4.*
Classifier: Development Status :: 5 - Production/Stable
Classifier: Intended Audience :: Developers
Classifier: License :: OSI Approved :: MIT License
Classifier: Programming Language :: Python :: 2
Classifier: Programming Language :: Python :: 2.7
Classifier: Programming Language :: Python :: 3
Classifier: Programming Language :: Python :: 3.5
Classifier: Programming Language :: Python :: 3.6
Classifier: Programming Language :: Python :: 3.7
Classifier: Programming Language :: Python :: 3.8
Classifier: Topic :: Utilities
Classifier: Typing :: Typed
Requires-Dist: contextlib2 (>=0.6.0,<0.7.0); python_version >= "2.7" and python_version < "3.0"
Requires-Dist: six (>=1.15.0,<2.0.0)
Requires-Dist: typing (>=3.7.4,<4.0.0); python_version >= "2.7" and python_version < "3.0"
Project-URL: Repository, https://github.com/tomgrin10/swap-exceptions
